{"expireTime":9007200888110942000,"key":"847b09aa4678a34a85288f0a4da6d2cc","val":{"name":"IMAGE_PROCESSING","inputPaths":["/Users/marekreid/Desktop/smithstbistro-staging/src/images/heroImage.jpg"],"outputDir":"/Users/marekreid/Desktop/smithstbistro-staging/public/static/7e35474ef38d80e47ba8751894fce11c","args":{"isLazy":false,"operations":[{"outputPath":"b1328/heroImage.jpg","args":{"height":913,"width":1809,"cropFocus":17,"toFormat":"jpg","fit":"cover"}},{"outputPath":"9b6f0/heroImage.jpg","args":{"height":1826,"width":3617,"cropFocus":17,"toFormat":"jpg","fit":"cover"}},{"outputPath":"13f4c/heroImage.jpg","args":{"height":3651,"width":7234,"cropFocus":17,"toFormat":"jpg","fit":"cover"}}],"pluginOptions":{"base64Width":20,"forceBase64Format":"","useMozJpeg":false,"stripMetadata":true,"lazyImageGeneration":true,"defaultQuality":50,"failOnError":true,"plugins":[]}}}}